acton_agent/__init__.py
acton_agent/logging_config.py
acton_agent/agent/__init__.py
acton_agent/agent/agent.py
acton_agent/agent/exceptions.py
acton_agent/agent/models.py
acton_agent/agent/prompts.py
acton_agent/agent/retry.py
acton_agent/agent/streaming_util.py
acton_agent/client/__init__.py
acton_agent/client/base.py
acton_agent/client/openai_client.py
acton_agent/client/openrouter.py
acton_agent/memory/__init__.py
acton_agent/memory/base.py
acton_agent/memory/simple.py
acton_agent/parsers/__init__.py
acton_agent/parsers/base.py
acton_agent/parsers/streaming.py
acton_agent/tools/__init__.py
acton_agent/tools/base.py
acton_agent/tools/function_tool.py
acton_agent/tools/models.py
acton_agent/tools/registry.py
acton_agent-0.0.23.dist-info/licenses/LICENSE
acton_agent-0.0.23.dist-info/METADATA
acton_agent-0.0.23.dist-info/WHEEL
acton_agent-0.0.23.dist-info/top_level.txt
acton_agent-0.0.23.dist-info/RECORD
